{
  "BTTPresetName" : "leapmotion",
  "BTTPresetUUID" : "7AD57C17-314C-4A46-964D-5A7752BEA83C",
  "BTTPresetContent" : [
    {
      "BTTAppBundleIdentifier" : "com.apple.ActivityMonitor",
      "BTTAppName" : "Activity Monitor",
      "BTTAppSpecificSettings" : {

      },
      "BTTTriggers" : [
        {
          "BTTGestureNotes" : "4h. Musicality: Thumbs Up",
          "BTTTriggerType" : 400,
          "BTTTriggerTypeDescription" : "2 Finger Up",
          "BTTTriggerClass" : "BTTTriggerTypeLeap",
          "BTTPredefinedActionType" : -1,
          "BTTPredefinedActionName" : "No Action",
          "BTTShortcutToSend" : "59,58,126",
          "BTTEnabled2" : 1,
          "BTTUUID" : "C507C3B8-E328-4EC6-95AB-69F94DA411DA",
          "BTTEnabled" : 0,
          "BTTRequiredModifierKeys" : 8388608,
          "BTTOrder" : 341,
          "BTTIconData" : "",
          "BTTAlternateIconData" : ""
        },
        {
          "BTTGestureNotes" : "4i. Musicality: Thumbs Down",
          "BTTTriggerType" : 403,
          "BTTTriggerTypeDescription" : "2 Finger Down",
          "BTTTriggerClass" : "BTTTriggerTypeLeap",
          "BTTPredefinedActionType" : -1,
          "BTTPredefinedActionName" : "No Action",
          "BTTShortcutToSend" : "59,58,125",
          "BTTEnabled2" : 1,
          "BTTUUID" : "7CBB3D8A-D19F-4285-B60F-FDDB687DF2AF",
          "BTTEnabled" : 1,
          "BTTRequiredModifierKeys" : 8388608,
          "BTTOrder" : 342,
          "BTTIconData" : "",
          "BTTAlternateIconData" : ""
        },
        {
          "BTTGestureNotes" : "1c. Application Expose",
          "BTTTriggerType" : 418,
          "BTTTriggerTypeDescription" : "3 Finger Up",
          "BTTTriggerClass" : "BTTTriggerTypeLeap",
          "BTTPredefinedActionType" : 6,
          "BTTPredefinedActionName" : "Application Expose",
          "BTTEnabled2" : 1,
          "BTTUUID" : "A61D5770-DE8E-4395-95AC-096A9729E0EF",
          "BTTEnabled" : 0,
          "BTTOrder" : 332,
          "BTTIconData" : "",
          "BTTAlternateIconData" : ""
        },
        {
          "BTTGestureNotes" : "2h. Restore Window Size",
          "BTTTriggerType" : 425,
          "BTTTriggerTypeDescription" : "5 Finger Down",
          "BTTTriggerClass" : "BTTTriggerTypeLeap",
          "BTTPredefinedActionType" : 84,
          "BTTPredefinedActionName" : "Restore Old Window Size",
          "BTTEnabled2" : 1,
          "BTTUUID" : "01BB557D-7E48-43AA-882E-70A719826724",
          "BTTEnabled" : 0,
          "BTTRequiredModifierKeys" : 1048576,
          "BTTOrder" : 333,
          "BTTIconData" : "",
          "BTTAlternateIconData" : ""
        },
        {
          "BTTGestureNotes" : "3b. Next Tab",
          "BTTTriggerType" : 420,
          "BTTTriggerTypeDescription" : "3 Finger Right",
          "BTTTriggerClass" : "BTTTriggerTypeLeap",
          "BTTPredefinedActionType" : -1,
          "BTTPredefinedActionName" : "No Action",
          "BTTShortcutToSend" : "56,55,30",
          "BTTEnabled2" : 1,
          "BTTUUID" : "B9A7325D-2926-47DA-89AD-BEB79A4F6293",
          "BTTEnabled" : 0,
          "BTTRequiredModifierKeys" : 1048576,
          "BTTOrder" : 340,
          "BTTIconData" : "",
          "BTTAlternateIconData" : ""
        },
        {
          "BTTGestureNotes" : "9b. Toggle Leap Mouse",
          "BTTTriggerType" : 427,
          "BTTTriggerTypeDescription" : "3 Finger Circles Counter Clockwise",
          "BTTTriggerClass" : "BTTTriggerTypeLeap",
          "BTTPredefinedActionType" : 143,
          "BTTPredefinedActionName" : "Enable \/ Disable Leap Motion Mouse Control",
          "BTTEnabled2" : 1,
          "BTTUUID" : "1535E2EF-5955-42E8-865F-1529EB8FF02F",
          "BTTEnabled" : 0,
          "BTTRequiredModifierKeys" : 8388608,
          "BTTOrder" : 337,
          "BTTAdditionalActions" : [
            {
              "BTTTriggerType" : -1,
              "BTTTriggerClass" : "BTTTriggerTypeLeap",
              "BTTPredefinedActionType" : 144,
              "BTTPredefinedActionName" : "Disable Gesture Recognition for X Seconds",
              "BTTDisableGestureRecognitionFor" : "0.50",
              "BTTEnabled2" : 1,
              "BTTUUID" : "2F0403A0-CB8B-4D79-A5EB-9C942068E3D1",
              "BTTEnabled" : 1,
              "BTTOrder" : 338,
              "BTTIconData" : "",
              "BTTAlternateIconData" : ""
            }
          ],
          "BTTIconData" : "",
          "BTTAlternateIconData" : ""
        },
        {
          "BTTGestureNotes" : "3a. Previous Tab",
          "BTTTriggerType" : 419,
          "BTTTriggerTypeDescription" : "3 Finger Left",
          "BTTTriggerClass" : "BTTTriggerTypeLeap",
          "BTTPredefinedActionType" : -1,
          "BTTPredefinedActionName" : "No Action",
          "BTTShortcutToSend" : "56,55,33",
          "BTTEnabled2" : 1,
          "BTTUUID" : "A3B4FF22-67F3-4EE5-97AD-5334BD15BE4E",
          "BTTEnabled" : 0,
          "BTTRequiredModifierKeys" : 1048576,
          "BTTOrder" : 339,
          "BTTIconData" : "",
          "BTTAlternateIconData" : ""
        }
      ]
    },
    {
      "BTTAppBundleIdentifier" : "BT.G",
      "BTTAppName" : "Global",
      "BTTAppSpecificSettings" : {

      },
      "BTTTriggers" : [
        {
          "BTTTriggerType" : 410,
          "BTTTriggerTypeDescription" : "1 Finger Up",
          "BTTTriggerClass" : "BTTTriggerTypeLeap",
          "BTTPredefinedActionType" : -1,
          "BTTPredefinedActionName" : "No Action",
          "BTTShortcutToSend" : "126",
          "BTTEnabled2" : 1,
          "BTTUUID" : "AB103E9C-E58E-4D5F-B919-93C1E23CC65E",
          "BTTEnabled" : 0,
          "BTTOrder" : 11,
          "BTTIconData" : "",
          "BTTAlternateIconData" : ""
        },
        {
          "BTTGestureNotes" : "3c. Application Switcher",
          "BTTTriggerType" : 426,
          "BTTTriggerTypeDescription" : "3 Finger Circles Clockwise",
          "BTTTriggerClass" : "BTTTriggerTypeLeap",
          "BTTPredefinedActionType" : 46,
          "BTTPredefinedActionName" : "Application Switcher",
          "BTTEnabled2" : 1,
          "BTTUUID" : "6C9EB8BC-670E-436C-BC78-424C689446EC",
          "BTTEnabled" : 0,
          "BTTOrder" : 7,
          "BTTIconData" : "",
          "BTTAlternateIconData" : ""
        },
        {
          "BTTTriggerType" : 411,
          "BTTTriggerTypeDescription" : "1 Finger Down",
          "BTTTriggerClass" : "BTTTriggerTypeLeap",
          "BTTPredefinedActionType" : -1,
          "BTTPredefinedActionName" : "No Action",
          "BTTShortcutToSend" : "125",
          "BTTEnabled2" : 1,
          "BTTUUID" : "537A2F6B-CF32-4131-BFD5-B67D8B9C86B9",
          "BTTEnabled" : 0,
          "BTTOrder" : 12,
          "BTTIconData" : "",
          "BTTAlternateIconData" : ""
        },
        {
          "BTTTriggerType" : 416,
          "BTTTriggerTypeDescription" : "1 Finger Tap",
          "BTTTriggerClass" : "BTTTriggerTypeLeap",
          "BTTPredefinedActionType" : -1,
          "BTTPredefinedActionName" : "No Action",
          "BTTShortcutToSend" : "49",
          "BTTEnabled2" : 1,
          "BTTUUID" : "D80DBCCD-46B3-4555-805D-7FC422E7D270",
          "BTTEnabled" : 0,
          "BTTOrder" : 15,
          "BTTIconData" : "",
          "BTTAlternateIconData" : ""
        },
        {
          "BTTGestureNotes" : "4c. Mute",
          "BTTTriggerType" : 403,
          "BTTTriggerTypeDescription" : "2 Finger Down",
          "BTTTriggerClass" : "BTTTriggerTypeLeap",
          "BTTPredefinedActionType" : 22,
          "BTTPredefinedActionName" : "Mute",
          "BTTEnabled2" : 1,
          "BTTUUID" : "407B4320-74B8-4B91-B20A-2E787524178A",
          "BTTEnabled" : 0,
          "BTTOrder" : 4,
          "BTTAdditionalActions" : [
            {
              "BTTTriggerType" : -1,
              "BTTTriggerClass" : "BTTTriggerTypeLeap",
              "BTTPredefinedActionType" : 144,
              "BTTPredefinedActionName" : "Disable Gesture Recognition for X Seconds",
              "BTTDisableGestureRecognitionFor" : "0.50",
              "BTTEnabled2" : 1,
              "BTTUUID" : "02713D8E-B62B-4974-9175-CC665065F377",
              "BTTEnabled" : 1,
              "BTTOrder" : 0,
              "BTTIconData" : "",
              "BTTAlternateIconData" : ""
            }
          ],
          "BTTIconData" : "",
          "BTTAlternateIconData" : ""
        },
        {
          "BTTTriggerType" : 422,
          "BTTTriggerTypeDescription" : "5 Finger Up",
          "BTTTriggerClass" : "BTTTriggerTypeLeap",
          "BTTPredefinedActionType" : 115,
          "BTTPredefinedActionName" : "Open Launchpad",
          "BTTEnabled2" : 1,
          "BTTUUID" : "CE2826F3-394D-4ADD-A70C-01F03D80E747",
          "BTTEnabled" : 0,
          "BTTOrder" : 0,
          "BTTAdditionalActions" : [
            {
              "BTTTriggerType" : -1,
              "BTTTriggerClass" : "BTTTriggerTypeLeap",
              "BTTPredefinedActionType" : 144,
              "BTTPredefinedActionName" : "Disable Gesture Recognition for X Seconds",
              "BTTDisableGestureRecognitionFor" : "0.50",
              "BTTEnabled2" : 1,
              "BTTUUID" : "E1C8F5C1-2CAA-461D-AFE5-04CAAEE44882",
              "BTTEnabled" : 1,
              "BTTOrder" : 0,
              "BTTIconData" : "",
              "BTTAlternateIconData" : ""
            }
          ],
          "BTTIconData" : "",
          "BTTAlternateIconData" : ""
        },
        {
          "BTTTriggerType" : 413,
          "BTTTriggerTypeDescription" : "1 Finger Right",
          "BTTTriggerClass" : "BTTTriggerTypeLeap",
          "BTTPredefinedActionType" : -1,
          "BTTPredefinedActionName" : "No Action",
          "BTTShortcutToSend" : "124",
          "BTTEnabled2" : 1,
          "BTTUUID" : "CAB2E798-0C44-48D3-B864-2FF9CCE66E4E",
          "BTTEnabled" : 1,
          "BTTOrder" : 9,
          "BTTIconData" : "",
          "BTTAlternateIconData" : ""
        },
        {
          "BTTTriggerType" : 404,
          "BTTTriggerTypeDescription" : "1 Finger (Small) Circle Clockwise",
          "BTTTriggerClass" : "BTTTriggerTypeLeap",
          "BTTPredefinedActionType" : -1,
          "BTTPredefinedActionName" : "No Action",
          "BTTShortcutToSend" : "63,121",
          "BTTEnabled2" : 1,
          "BTTUUID" : "F34BE18C-1148-4CAB-B6DC-FB08DCD89A18",
          "BTTEnabled" : 0,
          "BTTOrder" : 13,
          "BTTIconData" : "",
          "BTTAlternateIconData" : ""
        },
        {
          "BTTGestureNotes" : "4e. Previous Track",
          "BTTTriggerType" : 401,
          "BTTTriggerTypeDescription" : "2 Finger Left",
          "BTTTriggerClass" : "BTTTriggerTypeLeap",
          "BTTPredefinedActionType" : 26,
          "BTTPredefinedActionName" : "Previous",
          "BTTEnabled2" : 1,
          "BTTUUID" : "AC2AA997-298C-424A-8D63-F0EAC4E3F6EB",
          "BTTEnabled" : 0,
          "BTTOrder" : 5,
          "BTTAdditionalActions" : [
            {
              "BTTTriggerType" : -1,
              "BTTTriggerClass" : "BTTTriggerTypeLeap",
              "BTTPredefinedActionType" : 144,
              "BTTPredefinedActionName" : "Disable Gesture Recognition for X Seconds",
              "BTTDisableGestureRecognitionFor" : "0.50",
              "BTTEnabled2" : 1,
              "BTTUUID" : "6F082B49-5DFD-4EC0-93B2-F7D0FEF0B68F",
              "BTTEnabled" : 1,
              "BTTOrder" : 0,
              "BTTIconData" : "",
              "BTTAlternateIconData" : ""
            }
          ],
          "BTTIconData" : "",
          "BTTAlternateIconData" : ""
        },
        {
          "BTTGestureNotes" : "4d. Play\/Pause",
          "BTTTriggerType" : 400,
          "BTTTriggerTypeDescription" : "2 Finger Up",
          "BTTTriggerClass" : "BTTTriggerTypeLeap",
          "BTTPredefinedActionType" : 23,
          "BTTPredefinedActionName" : "Play\/Pause",
          "BTTEnabled2" : 1,
          "BTTUUID" : "C05FA717-3F51-4583-868F-E5B7CE52F88C",
          "BTTEnabled" : 0,
          "BTTOrder" : 3,
          "BTTAdditionalActions" : [
            {
              "BTTTriggerType" : -1,
              "BTTTriggerClass" : "BTTTriggerTypeLeap",
              "BTTPredefinedActionType" : 144,
              "BTTPredefinedActionName" : "Disable Gesture Recognition for X Seconds",
              "BTTDisableGestureRecognitionFor" : "0.50",
              "BTTEnabled2" : 1,
              "BTTUUID" : "C57EB748-A9B3-43A5-8CC5-C800EBFC97AF",
              "BTTEnabled" : 1,
              "BTTOrder" : 0,
              "BTTIconData" : "",
              "BTTAlternateIconData" : ""
            }
          ],
          "BTTIconData" : "",
          "BTTAlternateIconData" : ""
        },
        {
          "BTTTriggerType" : 412,
          "BTTTriggerTypeDescription" : "1 Finger Left",
          "BTTTriggerClass" : "BTTTriggerTypeLeap",
          "BTTPredefinedActionType" : -1,
          "BTTPredefinedActionName" : "No Action",
          "BTTShortcutToSend" : "123",
          "BTTEnabled2" : 1,
          "BTTUUID" : "7B232BDE-5C5E-4552-B7D6-97E8DFD74717",
          "BTTEnabled" : 1,
          "BTTOrder" : 10,
          "BTTIconData" : "",
          "BTTAlternateIconData" : ""
        },
        {
          "BTTGestureNotes" : "4a. Volume Down",
          "BTTTriggerType" : 407,
          "BTTTriggerTypeDescription" : "2 Finger (Small) Circles Counter Clockwise",
          "BTTTriggerClass" : "BTTTriggerTypeLeap",
          "BTTPredefinedActionType" : 25,
          "BTTPredefinedActionName" : "Volume Down",
          "BTTEnabled2" : 1,
          "BTTUUID" : "57959D2B-E9D3-4240-A7B4-900C36A5C55E",
          "BTTEnabled" : 0,
          "BTTOrder" : 1,
          "BTTIconData" : "",
          "BTTAlternateIconData" : ""
        },
        {
          "BTTTriggerType" : 405,
          "BTTTriggerTypeDescription" : "1 Finger (Small) Circle Counter Clockwise",
          "BTTTriggerClass" : "BTTTriggerTypeLeap",
          "BTTPredefinedActionType" : -1,
          "BTTPredefinedActionName" : "No Action",
          "BTTShortcutToSend" : "63,116",
          "BTTEnabled2" : 1,
          "BTTUUID" : "8B6BAE0D-B0D7-4CD3-8333-D1076ED3C9DB",
          "BTTEnabled" : 0,
          "BTTOrder" : 14,
          "BTTIconData" : "",
          "BTTAlternateIconData" : ""
        },
        {
          "BTTGestureNotes" : "3c. Application Switcher (backward)",
          "BTTTriggerType" : 427,
          "BTTTriggerTypeDescription" : "3 Finger Circles Counter Clockwise",
          "BTTTriggerClass" : "BTTTriggerTypeLeap",
          "BTTPredefinedActionType" : 142,
          "BTTPredefinedActionName" : "Application Switcher Backward (After Forward)",
          "BTTEnabled2" : 1,
          "BTTUUID" : "30CE2F18-468A-48EC-BDB6-E5813BF0BDCF",
          "BTTEnabled" : 0,
          "BTTOrder" : 8,
          "BTTIconData" : "",
          "BTTAlternateIconData" : ""
        },
        {
          "BTTGestureNotes" : "4f. Next Track",
          "BTTTriggerType" : 402,
          "BTTTriggerTypeDescription" : "2 Finger Right",
          "BTTTriggerClass" : "BTTTriggerTypeLeap",
          "BTTPredefinedActionType" : 27,
          "BTTPredefinedActionName" : "Next",
          "BTTEnabled2" : 1,
          "BTTUUID" : "41C5498A-6D68-4D7B-B3F4-ADCD87C59241",
          "BTTEnabled" : 0,
          "BTTOrder" : 6,
          "BTTAdditionalActions" : [
            {
              "BTTTriggerType" : -1,
              "BTTTriggerClass" : "BTTTriggerTypeLeap",
              "BTTPredefinedActionType" : 144,
              "BTTPredefinedActionName" : "Disable Gesture Recognition for X Seconds",
              "BTTDisableGestureRecognitionFor" : "0.50",
              "BTTEnabled2" : 1,
              "BTTUUID" : "D3CD38BE-5E9C-4EDB-96D4-0F76F0F9FAA3",
              "BTTEnabled" : 1,
              "BTTOrder" : 0,
              "BTTIconData" : "",
              "BTTAlternateIconData" : ""
            }
          ],
          "BTTIconData" : "",
          "BTTAlternateIconData" : ""
        },
        {
          "BTTGestureNotes" : "4b. Volume Up",
          "BTTTriggerType" : 406,
          "BTTTriggerTypeDescription" : "2 Finger (Small) Circles Clockwise",
          "BTTTriggerClass" : "BTTTriggerTypeLeap",
          "BTTPredefinedActionType" : 24,
          "BTTPredefinedActionName" : "Volume Up",
          "BTTEnabled2" : 1,
          "BTTUUID" : "933ADB7C-4A2E-49DE-B6E9-64A0347F7CE8",
          "BTTEnabled" : 0,
          "BTTOrder" : 2,
          "BTTIconData" : "",
          "BTTAlternateIconData" : ""
        }
      ]
    },
    {
      "BTTAppBundleIdentifier" : "com.apple.finder",
      "BTTAppName" : "Finder",
      "BTTAppSpecificSettings" : {

      },
      "BTTTriggers" : [

      ]
    },
    {
      "BTTAppBundleIdentifier" : "com.googlecode.iterm2",
      "BTTAppName" : "iTerm",
      "BTTAppSpecificSettings" : {

      },
      "BTTTriggers" : [

      ]
    },
    {
      "BTTAppBundleIdentifier" : "com.google.Chrome",
      "BTTAppName" : "Google Chrome",
      "BTTAppSpecificSettings" : {

      },
      "BTTTriggers" : [
        {
          "BTTTriggerType" : -1,
          "BTTTriggerClass" : "BTTTriggerTypeLeap",
          "BTTPredefinedActionType" : -1,
          "BTTPredefinedActionName" : "No Action",
          "BTTEnabled2" : 1,
          "BTTUUID" : "C53A719D-CF2F-4615-ADFF-E938B9474422",
          "BTTEnabled" : 1,
          "BTTOrder" : 1,
          "BTTIconData" : "",
          "BTTAlternateIconData" : ""
        },
        {
          "BTTTriggerType" : 402,
          "BTTTriggerTypeDescription" : "2 Finger Right",
          "BTTTriggerClass" : "BTTTriggerTypeLeap",
          "BTTPredefinedActionType" : 78,
          "BTTPredefinedActionName" : "3F Swipe Right (Page Forward)",
          "BTTEnabled2" : 1,
          "BTTUUID" : "4FBB082C-667B-49B6-8FFC-734FDD60D487",
          "BTTEnabled" : 0,
          "BTTOrder" : 345,
          "BTTAdditionalActions" : [
            {
              "BTTTriggerType" : -1,
              "BTTTriggerClass" : "BTTTriggerTypeLeap",
              "BTTPredefinedActionType" : 144,
              "BTTPredefinedActionName" : "Disable Gesture Recognition for X Seconds",
              "BTTDisableGestureRecognitionFor" : "0.50",
              "BTTEnabled2" : 1,
              "BTTUUID" : "02F6FFDD-E24D-4A1E-8FA5-48034DDA2AD8",
              "BTTEnabled" : 1,
              "BTTOrder" : 346,
              "BTTIconData" : "",
              "BTTAlternateIconData" : ""
            }
          ],
          "BTTIconData" : "",
          "BTTAlternateIconData" : ""
        },
        {
          "BTTGestureNotes" : "focus on location bar",
          "BTTTriggerType" : 414,
          "BTTTriggerTypeDescription" : "5 Finger Tap",
          "BTTTriggerClass" : "BTTTriggerTypeLeap",
          "BTTPredefinedActionType" : -1,
          "BTTPredefinedActionName" : "No Action",
          "BTTShortcutToSend" : "55,37",
          "BTTEnabled2" : 1,
          "BTTUUID" : "9961820B-B96F-494D-8081-7F583A7820DB",
          "BTTEnabled" : 0,
          "BTTOrder" : 0,
          "BTTIconData" : "",
          "BTTAlternateIconData" : ""
        },
        {
          "BTTTriggerType" : 401,
          "BTTTriggerTypeDescription" : "2 Finger Left",
          "BTTTriggerClass" : "BTTTriggerTypeLeap",
          "BTTPredefinedActionType" : 77,
          "BTTPredefinedActionName" : "3F Swipe Left (Page Back)",
          "BTTEnabled2" : 1,
          "BTTUUID" : "DF6F879D-A33E-4769-903E-23624C944984",
          "BTTEnabled" : 0,
          "BTTOrder" : 343,
          "BTTAdditionalActions" : [
            {
              "BTTTriggerType" : -1,
              "BTTTriggerClass" : "BTTTriggerTypeLeap",
              "BTTPredefinedActionType" : 144,
              "BTTPredefinedActionName" : "Disable Gesture Recognition for X Seconds",
              "BTTDisableGestureRecognitionFor" : "0.50",
              "BTTEnabled2" : 1,
              "BTTUUID" : "55B0EB51-DA07-45D7-831D-10BEC58C81D9",
              "BTTEnabled" : 1,
              "BTTOrder" : 344,
              "BTTIconData" : "",
              "BTTAlternateIconData" : ""
            }
          ],
          "BTTIconData" : "",
          "BTTAlternateIconData" : ""
        }
      ]
    }
  ],
  "BTTPresetSnapAreas" : [

  ]
}